README.rst
setup.py
django_languages/__init__.py
django_languages/fields.py
django_languages/languages.py
django_languages/models.py
django_languages/tests.py
django_languages.egg-info/PKG-INFO
django_languages.egg-info/SOURCES.txt
django_languages.egg-info/dependency_links.txt
django_languages.egg-info/not-zip-safe
django_languages.egg-info/top_level.txt