Metadata-Version: 1.1
Name: django-languages
Version: 0.1
Summary: Provides a language field for Django models.
Home-page: http://bitbucket.org/basaundi/django-languages/
Author: Ander Martinez
Author-email: ander.basaundi@gmail.com
License: UNKNOWN
Platform: UNKNOWN
Classifier: Development Status :: 4 - Beta
Classifier: Environment :: Web Environment
Classifier: Intended Audience :: Developers
Classifier: License :: OSI Approved :: MIT License
Classifier: Operating System :: OS Independent
Classifier: Programming Language :: Python
Classifier: Framework :: Django
